datalift/__init__.py
datalift/containers.py
datalift/datalift.py
datalift/storages/__init__.py
datalift/storages/base.py
datalift/storages/utils.py
datalift/storages/infra/__init__.py
datalift/storages/infra/dummy.py
datalift/storages/infra/ftp.py
datalift-0.1.2.dist-info/METADATA
datalift-0.1.2.dist-info/WHEEL
datalift-0.1.2.dist-info/entry_points.txt
datalift-0.1.2.dist-info/top_level.txt
datalift-0.1.2.dist-info/RECORD
