Metadata-Version: 2.1
Name: datalift
Version: 0.1.2
Summary: Datalift it is a command-line tool designed to tools outputs to a storage service. Users can input data either by passing a filename or through stdout from another tool.
Home-page: UNKNOWN
Author: Samuel López Saura
Author-email: samuellopezsaura@gmail.com
License: MIT
Platform: UNKNOWN
Classifier: Programming Language :: Python :: 3
Classifier: License :: OSI Approved :: MIT License
Classifier: Operating System :: OS Independent
Requires-Dist: dependency-injector (<5.0,>=4.41)
